LICENSE
MANIFEST.in
README.rst
pyproject.toml
setup.py
cxx/pybind.cxx
cxx/utils/files.cxx
cxx/utils/files.h
cxx/utils/files.hxx
cxx/utils/manip.cxx
cxx/utils/manip.h
cxx/utils/maths.h
cxx/utils/maths.hxx
cxx/utils/sparse.cxx
cxx/utils/sparse.h
cxx/utils/sparse.hxx
cxx/utils/text.cxx
cxx/utils/text.h
cxx/vhash/vhash.cxx
cxx/vhash/vhash.h
vhash/__init__.py
vhash/vhash.py
vhash.egg-info/PKG-INFO
vhash.egg-info/SOURCES.txt
vhash.egg-info/dependency_links.txt
vhash.egg-info/requires.txt
vhash.egg-info/top_level.txt