Metadata-Version: 2.1
Name: vhash
Version: 0.0.27
Summary: hash tables for vectorizing text-based documents
Author: Mike Powell PhD
Author-email: mike@lakeslegendaries.com
License: MIT License
Project-URL: Documentation, https://lakes-legendaries.github.io/vhash/
Project-URL: GitHub, https://github.com/lakes-legendaries/vhash/
Project-URL: Bug Tracker, https://github.com/lakes-legendaries/vhash/issues
Classifier: Programming Language :: Python :: 3
Classifier: License :: OSI Approved :: MIT License
Classifier: Operating System :: OS Independent
Requires-Python: >=3.8
License-File: LICENSE
